pbipandas/__init__.py
pbipandas/client.py
pbipandas/auth/__init__.py
pbipandas/auth/base_client.py
pbipandas/bulks/__init__.py
pbipandas/bulks/bulk_client.py
pbipandas/dataflow/__init__.py
pbipandas/dataflow/dataflow_client.py
pbipandas/dataset/__init__.py
pbipandas/dataset/dataset_client.py
pbipandas/report/__init__.py
pbipandas/report/report_client.py
pbipandas/utils/__init__.py
pbipandas/utils/connection_utils.py
pbipandas/utils/info_utils.py
pbipandas/workspace/__init__.py
pbipandas/workspace/workspace_client.py
pbipandas-1.0.2.dist-info/licenses/LICENSE
pbipandas-1.0.2.dist-info/METADATA
pbipandas-1.0.2.dist-info/WHEEL
pbipandas-1.0.2.dist-info/top_level.txt
pbipandas-1.0.2.dist-info/RECORD
