Metadata-Version: 2.4
Name: pbipandas
Version: 1.0.2
Summary: A Python wrapper for Power BI REST API with Pandas integration
Author-email: Harry Dinh <hoangdinh.2710@gmail.com>
License: MIT
Project-URL: Homepage, https://github.com/hoangdinh2710/pbipandas
Project-URL: Repository, https://github.com/hoangdinh2710/pbipandas
Project-URL: Issues, https://github.com/hoangdinh2710/pbipandas/issues
Requires-Python: >=3.8
License-File: LICENSE
Requires-Dist: requests
Requires-Dist: pandas
Dynamic: license-file
